odoo9_addon_partner_multi_relation-9.0.1.1.1-py2.7-nspkg.pth
odoo_addons/partner_multi_relation/__openerp__.py
odoo_addons/partner_multi_relation/__init__.py
odoo_addons/partner_multi_relation/README.rst
odoo_addons/partner_multi_relation/security/ir.model.access.csv
odoo_addons/partner_multi_relation/models/res_partner_relation.py
odoo_addons/partner_multi_relation/models/res_partner.py
odoo_addons/partner_multi_relation/models/res_partner_relation_type.py
odoo_addons/partner_multi_relation/models/__init__.py
odoo_addons/partner_multi_relation/models/res_partner_relation_type_selection.py
odoo_addons/partner_multi_relation/models/res_partner_relation_all.py
odoo_addons/partner_multi_relation/i18n/it.po
odoo_addons/partner_multi_relation/i18n/es.po
odoo_addons/partner_multi_relation/i18n/partner_multi_relation.pot
odoo_addons/partner_multi_relation/i18n/sl.po
odoo_addons/partner_multi_relation/i18n/da.po
odoo_addons/partner_multi_relation/i18n/nl.po
odoo_addons/partner_multi_relation/i18n/de.po
odoo_addons/partner_multi_relation/i18n/fr.po
odoo_addons/partner_multi_relation/i18n/pt_BR.po
odoo_addons/partner_multi_relation/i18n/fi.po
odoo_addons/partner_multi_relation/views/menu.xml
odoo_addons/partner_multi_relation/views/res_partner_relation_all.xml
odoo_addons/partner_multi_relation/views/res_partner_relation_type.xml
odoo_addons/partner_multi_relation/views/res_partner.xml
odoo_addons/partner_multi_relation/data/demo.xml
odoo_addons/partner_multi_relation/tests/test_partner_relation.py
odoo_addons/partner_multi_relation/tests/__init__.py
odoo_addons/partner_multi_relation/tests/test_partner_relation_common.py
odoo_addons/partner_multi_relation/tests/test_partner_relation_all.py
odoo_addons/partner_multi_relation/tests/test_partner_search.py
odoo_addons/partner_multi_relation/static/description/icon.png
odoo9_addon_partner_multi_relation-9.0.1.1.1.dist-info/top_level.txt
odoo9_addon_partner_multi_relation-9.0.1.1.1.dist-info/WHEEL
odoo9_addon_partner_multi_relation-9.0.1.1.1.dist-info/RECORD
odoo9_addon_partner_multi_relation-9.0.1.1.1.dist-info/metadata.json
odoo9_addon_partner_multi_relation-9.0.1.1.1.dist-info/DESCRIPTION.rst
odoo9_addon_partner_multi_relation-9.0.1.1.1.dist-info/METADATA
odoo9_addon_partner_multi_relation-9.0.1.1.1.dist-info/namespace_packages.txt
